OTPLessAuthSDK.py
OTPLessAuthSDK-0.3.3.dist-info/LICENSE
OTPLessAuthSDK-0.3.3.dist-info/METADATA
OTPLessAuthSDK-0.3.3.dist-info/WHEEL
OTPLessAuthSDK-0.3.3.dist-info/top_level.txt
OTPLessAuthSDK-0.3.3.dist-info/RECORD
