Metadata-Version: 2.1
Name: OTPLessAuthSDK
Version: 0.3.3
Summary: otpless-auth-sdk
Author: OTPless
Classifier: Programming Language :: Python :: 3
Classifier: License :: OSI Approved :: MIT License
Classifier: Operating System :: OS Independent
Requires-Python: >=3
License-File: LICENSE
Requires-Dist: requests
Requires-Dist: PyJWT
Requires-Dist: rsa
Requires-Dist: cryptography
